Workbook

Sheet products
A1: Number | B1: Name | C1: CodeNr | D1: CodeTxt | E1: ConsumptionCategories | F1: TradeMargin | G1: TransportMargin | H1: Waste
A2: 1 | B2: Paddy rice | C2: p01.a | D2: C_PARI | E2: Food | F2: 0 | G2: 0 | H2: 0
A3: 2 | B3: Wheat | C3: p01.b | D3: C_WHEA | E3: Food | F3: 0 | G3: 0 | H3: 0
A4: 3 | B4: Cereal grains nec | C4: p01.c | D4: C_OCER | E4: Food | F4: 0 | G4: 0 | H4: 0
A5: 4 | B5: Vegetables, fruit, nuts | C5: p01.d | D5: C_FVEG | E5: Food | F5: 0 | G5: 0 | H5: 0
A6: 5 | B6: Oil seeds | C6: p01.e | D6: C_OILS | E6: Food | F6: 0 | G6: 0 | H6: 0
A7: 6 | B7: Sugar cane, sugar beet | C7: p01.f | D7: C_SUGB | E7: Food | F7: 0 | G7: 0 | H7: 0
A8: 7 | B8: Plant-based fibers | C8: p01.g | D8: C_FIBR | E8: Food | F8: 0 | G8: 0 | H8: 0
A9: 8 | B9: Crops nec | C9: p01.h | D9: C_OTCR | E9: Food | F9: 0 | G9: 0 | H9: 0
A10: 9 | B10: Cattle | C10: p01.i | D10: C_CATL | E10: Food | F10: 0 | G10: 0 | H10: 0
A11: 10 | B11: Pigs | C11: p01.j | D11: C_PIGS | E11: Food | F11: 0 | G11: 0 | H11: 0
A12: 11 | B12: Poultry | C12: p01.k | D12: C_PLTR | E12: Food | F12: 0 | G12: 0 | H12: 0
A13: 12 | B13: Meat animals nec | C13: p01.l | D13: C_OMEA | E13: Food | F13: 0 | G13: 0 | H13: 0
... A201: 200 | B201: Extra-territorial organizations and bodies | C201: p99 | D201: C_EXTO | E201: Services | F201: 0 | G201: 0 | H201: 0

Sheet industries
A1: Number | B1: Name | C1: CodeNr | D1: CodeTxt | E1: ISIC_A | F1: ISIC_B | G1: ISIC_C | H1: ISIC_D | I1: ISIC_E | J1: ISIC_F | K1: ISIC_G_H | L1: ISIC_I | M1: ISIC_J_K | N1: ISIC_L | O1: ISIC_M_N_O | P1: ISIC_P | Q1: ISIC NAME | R1: ConsumptionCategories
A2: 1 | B2: Cultivation of paddy rice | C2: i01.a | D2: A_PARI | E2: 1 | F2: 0 | G2: 0 | H2: 0 | I2: 0 | J2: 0 | K2: 0 | L2: 0 | M2: 0 | N2: 0 | O2: 0 | P2: 0 | Q2: Agriculture, hunting and related service activities (01) | R2: Food
A3: 2 | B3: Cultivation of wheat | C3: i01.b | D3: A_WHEA | E3: 1 | F3: 0 | G3: 0 | H3: 0 | I3: 0 | J3: 0 | K3: 0 | L3: 0 | M3: 0 | N3: 0 | O3: 0 | P3: 0 | Q3: Agriculture, hunting and related service activities (01) | R3: Food
A4: 3 | B4: Cultivation of cereal grains nec | C4: i01.c | D4: A_OCER | E4: 1 | F4: 0 | G4: 0 | H4: 0 | I4: 0 | J4: 0 | K4: 0 | L4: 0 | M4: 0 | N4: 0 | O4: 0 | P4: 0 | Q4: Agriculture, hunting and related service activities (01) | R4: Food
A5: 4 | B5: Cultivation of vegetables, fruit, nuts | C5: i01.d | D5: A_FVEG | E5: 1 | F5: 0 | G5: 0 | H5: 0 | I5: 0 | J5: 0 | K5: 0 | L5: 0 | M5: 0 | N5: 0 | O5: 0 | P5: 0 | Q5: Agriculture, hunting and related service activities (01) | R5: Food
A6: 5 | B6: Cultivation of oil seeds | C6: i01.e | D6: A_OILS | E6: 1 | F6: 0 | G6: 0 | H6: 0 | I6: 0 | J6: 0 | K6: 0 | L6: 0 | M6: 0 | N6: 0 | O6: 0 | P6: 0 | Q6: Agriculture, hunting and related service activities (01) | R6: Food
A7: 6 | B7: Cultivation of sugar cane, sugar beet | C7: i01.f | D7: A_SUGB | E7: 1 | F7: 0 | G7: 0 | H7: 0 | I7: 0 | J7: 0 | K7: 0 | L7: 0 | M7: 0 | N7: 0 | O7: 0 | P7: 0 | Q7: Agriculture, hunting and related service activities (01) | R7: Food
A8: 7 | B8: Cultivation of plant-based fibers | C8: i01.g | D8: A_FIBR | E8: 1 | F8: 0 | G8: 0 | H8: 0 | I8: 0 | J8: 0 | K8: 0 | L8: 0 | M8: 0 | N8: 0 | O8: 0 | P8: 0 | Q8: Agriculture, hunting and related service activities (01) | R8: Food
A9: 8 | B9: Cultivation of crops nec | C9: i01.h | D9: A_OTCR | E9: 1 | F9: 0 | G9: 0 | H9: 0 | I9: 0 | J9: 0 | K9: 0 | L9: 0 | M9: 0 | N9: 0 | O9: 0 | P9: 0 | Q9: Agriculture, hunting and related service activities (01) | R9: Food
A10: 9 | B10: Cattle farming | C10: i01.i | D10: A_CATL | E10: 1 | F10: 0 | G10: 0 | H10: 0 | I10: 0 | J10: 0 | K10: 0 | L10: 0 | M10: 0 | N10: 0 | O10: 0 | P10: 0 | Q10: Agriculture, hunting and related service activities (01) | R10: Food
A11: 10 | B11: Pigs farming | C11: i01.j | D11: A_PIGS | E11: 1 | F11: 0 | G11: 0 | H11: 0 | I11: 0 | J11: 0 | K11: 0 | L11: 0 | M11: 0 | N11: 0 | O11: 0 | P11: 0 | Q11: Agriculture, hunting and related service activities (01) | R11: Food
A12: 11 | B12: Poultry farming | C12: i01.k | D12: A_PLTR | E12: 1 | F12: 0 | G12: 0 | H12: 0 | I12: 0 | J12: 0 | K12: 0 | L12: 0 | M12: 0 | N12: 0 | O12: 0 | P12: 0 | Q12: Agriculture, hunting and related service activities (01) | R12: Food
A13: 12 | B13: Meat animals nec | C13: i01.l | D13: A_OMEA | E13: 1 | F13: 0 | G13: 0 | H13: 0 | I13: 0 | J13: 0 | K13: 0 | L13: 0 | M13: 0 | N13: 0 | O13: 0 | P13: 0 | Q13: Agriculture, hunting and related service activities (01) | R13: Food
... A164: 163 | B164: Extra-territorial organizations and bodies | C164: i99 | D164: A_EXTO | E164: 0 | F164: 0 | G164: 0 | H164: 0 | I164: 0 | J164: 0 | K164: 0 | L164: 0 | M164: 0 | N164: 1 | O164: 0 | P164: 0 | Q164: Public administration and defense; compulsory social security (L) | R164: Services

Sheet valueadded_mat
A1: Number | B1: Name | C1: CodeNr | D1: CodeTxt | E1: tax | F1: sub | G1: tax_sub | H1: tax_ly_sum | I1: comp | J1: opersurplus | K1: pure | L1: allw | M1: sub_cat | N1: empty | O1: can_be_negative
A2: 201 | B2: Taxes less subsidies on products purchased: Total | C2: w01 | D2: T_TLSA | E2: 1 | F2: 0 | G2: =IF(OR(E2, F2),1,0) -> 1 | H2: 1 | I2: 0 | J2: 0 | K2: 0 | L2: =IF(OR(K2,G2),1,0) -> 1 | M2: 0 | N2: =IF(OR(E2:L2),0,1) -> 0 | O2: 1
A3: 202 | B3: Taxes on products purchased | C3: w01.a | D3: T_TAXA | E3: 1 | F3: 0 | G3: =IF(OR(E3, F3),1,0) -> 1 | H3: 0 | I3: 0 | J3: 0 | K3: 0 | L3: =IF(OR(K3,G3),1,0) -> 1 | M3: 1 | N3: =IF(OR(E3:L3),0,1) -> 0 | O3: 1
A4: 203 | B4: Subsidies on products purchased | C4: w01.b | D4: T_SUBA | E4: 0 | F4: 1 | G4: =IF(OR(E4, F4),1,0) -> 1 | H4: 0 | I4: 0 | J4: 0 | K4: 0 | L4: =IF(OR(K4,G4),1,0) -> 1 | M4: 1 | N4: =IF(OR(E4:L4),0,1) -> 0 | O4: 1
A5: 204 | B5: Other net taxes on production | C5: w02 | D5: V_ONTP | E5: 1 | F5: 0 | G5: =IF(OR(E5, F5),1,0) -> 1 | H5: 0 | I5: 0 | J5: 0 | K5: 1 | L5: =IF(OR(K5,G5),1,0) -> 1 | M5: 0 | N5: =IF(OR(E5:L5),0,1) -> 0 | O5: 1
A6: 205 | B6: Compensation of employees; wages, salaries, & employers' social contributions: Total | C6: w03 | D6: V_WAGE | E6: 0 | F6: 0 | G6: =IF(OR(E6, F6),1,0) -> 0 | H6: 0 | I6: 1 | J6: 0 | K6: 1 | L6: =IF(OR(K6,G6),1,0) -> 1 | M6: 0 | N6: =IF(OR(E6:L6),0,1) -> 0 | O6: 0
A7: 206 | B7: Compensation of employees; wages, salaries, & employers' social contributions: Low-skilled | C7: w03.a | D7: V_WALS | E7: 0 | F7: 0 | G7: =IF(OR(E7, F7),1,0) -> 0 | H7: 0 | I7: 1 | J7: 0 | K7: 1 | L7: =IF(OR(K7,G7),1,0) -> 1 | M7: 1 | N7: =IF(OR(E7:L7),0,1) -> 0 | O7: 0
A8: 207 | B8: Compensation of employees; wages, salaries, & employers' social contributions: Medium-skilled | C8: w03.b | D8: V_WAMS | E8: 0 | F8: 0 | G8: =IF(OR(E8, F8),1,0) -> 0 | H8: 0 | I8: 1 | J8: 0 | K8: 1 | L8: =IF(OR(K8,G8),1,0) -> 1 | M8: 1 | N8: =IF(OR(E8:L8),0,1) -> 0 | O8: 0
A9: 208 | B9: Compensation of employees; wages, salaries, & employers' social contributions: High-skilled | C9: w03.c | D9: V_WAHS | E9: 0 | F9: 0 | G9: =IF(OR(E9, F9),1,0) -> 0 | H9: 0 | I9: 1 | J9: 0 | K9: 1 | L9: =IF(OR(K9,G9),1,0) -> 1 | M9: 1 | N9: =IF(OR(E9:L9),0,1) -> 0 | O9: 0
A10: 209 | B10: Operating surplus: Consumption of fixed capital | C10: w04.a | D10: V_COFC | E10: 0 | F10: 0 | G10: =IF(OR(E10, F10),1,0) -> 0 | H10: 0 | I10: 0 | J10: 1 | K10: 1 | L10: =IF(OR(K10,G10),1,0) -> 1 | M10: 0 | N10: =IF(OR(E10:L10),0,1) -> 0 | O10: 0
A11: 210 | B11: Operating surplus: Rents on land | C11: w04.b | D11: V_RENL | E11: 0 | F11: 0 | G11: =IF(OR(E11, F11),1,0) -> 0 | H11: 0 | I11: 0 | J11: 1 | K11: 1 | L11: =IF(OR(K11,G11),1,0) -> 1 | M11: 0 | N11: =IF(OR(E11:L11),0,1) -> 0 | O11: 0
A12: 211 | B12: Operating surplus: Royalties on resources | C12: w04.c | D12: V_ROYR | E12: 0 | F12: 0 | G12: =IF(OR(E12, F12),1,0) -> 0 | H12: 0 | I12: 0 | J12: 1 | K12: 1 | L12: =IF(OR(K12,G12),1,0) -> 1 | M12: 0 | N12: =IF(OR(E12:L12),0,1) -> 0 | O12: 0
A13: 212 | B13: Operating surplus: Remaining net operating surplus | C13: w04.d | D13: V_NOPS | E13: 0 | F13: 0 | G13: =IF(OR(E13, F13),1,0) -> 0 | H13: 0 | I13: 0 | J13: 1 | K13: 1 | L13: =IF(OR(K13,G13),1,0) -> 1 | M13: 0 | N13: =IF(OR(E13:L13),0,1) -> 0 | O13: 1

Sheet valueadded_creea
A1: Number | B1: Name | C1: CodeNr | D1: CodeTxt | E1: tax | F1: sub | G1: tax_sub | H1: comp | I1: opersurplus | J1: pure | K1: allw | L1: allz | M1: sat_comp | N1: sat_emp | O1: sat_cap | P1: sub_cat | Q1: empty
A2: 201 | B2: Taxes less subsidies on products purchased: Total | C2: w01 | D2: T_TLSA | E2: 1 | F2: 0 | G2: =IF(OR(E2, F2),1,0) -> 1 | H2: 0 | I2: 0 | J2: 0 | K2: =IF(OR(J2,G2),1,0) -> 1 | L2: 0 | M2: 0 | N2: 0 | O2: 0 | P2: 0 | Q2: =IF(OR(E2:O2),0,1) -> 0
A3: 202 | B3: Taxes on products purchased | C3: w01.a | D3: T_TAXA | E3: 1 | F3: 0 | G3: =IF(OR(E3, F3),1,0) -> 1 | H3: 0 | I3: 0 | J3: 0 | K3: =IF(OR(J3,G3),1,0) -> 1 | L3: 0 | M3: 0 | N3: 0 | O3: 0 | P3: 1 | Q3: =IF(OR(E3:O3),0,1) -> 0
A4: 203 | B4: Subsidies on products purchased | C4: w01.b | D4: T_SUBA | E4: 0 | F4: 1 | G4: =IF(OR(E4, F4),1,0) -> 1 | H4: 0 | I4: 0 | J4: 0 | K4: =IF(OR(J4,G4),1,0) -> 1 | L4: 0 | M4: 0 | N4: 0 | O4: 0 | P4: 1 | Q4: =IF(OR(E4:O4),0,1) -> 0
A5: 204 | B5: Other net taxes on production | C5: w02 | D5: V_ONTP | E5: 1 | F5: 0 | G5: =IF(OR(E5, F5),1,0) -> 1 | H5: 0 | I5: 0 | J5: 1 | K5: =IF(OR(J5,G5),1,0) -> 1 | L5: 0 | M5: 0 | N5: 0 | O5: 0 | P5: 0 | Q5: =IF(OR(E5:O5),0,1) -> 0
A6: 205 | B6: Compensation of employees; wages, salaries, & employers' social contributions: Total | C6: w03 | D6: V_WAGE | E6: 0 | F6: 0 | G6: =IF(OR(E6, F6),1,0) -> 0 | H6: 1 | I6: 0 | J6: 1 | K6: =IF(OR(J6,G6),1,0) -> 1 | L6: 0 | M6: 0 | N6: 0 | O6: 0 | P6: 0 | Q6: =IF(OR(E6:O6),0,1) -> 0
A7: 206 | B7: Compensation of employees; wages, salaries, & employers' social contributions: Low-skilled | C7: w03.a | D7: V_WALS | E7: 0 | F7: 0 | G7: =IF(OR(E7, F7),1,0) -> 0 | H7: 1 | I7: 0 | J7: 1 | K7: =IF(OR(J7,G7),1,0) -> 1 | L7: 0 | M7: 0 | N7: 0 | O7: 0 | P7: 1 | Q7: =IF(OR(E7:O7),0,1) -> 0
A8: 207 | B8: Compensation of employees; wages, salaries, & employers' social contributions: Medium-skilled | C8: w03.b | D8: V_WAMS | E8: 0 | F8: 0 | G8: =IF(OR(E8, F8),1,0) -> 0 | H8: 1 | I8: 0 | J8: 1 | K8: =IF(OR(J8,G8),1,0) -> 1 | L8: 0 | M8: 0 | N8: 0 | O8: 0 | P8: 1 | Q8: =IF(OR(E8:O8),0,1) -> 0
A9: 208 | B9: Compensation of employees; wages, salaries, & employers' social contributions: High-skilled | C9: w03.c | D9: V_WAHS | E9: 0 | F9: 0 | G9: =IF(OR(E9, F9),1,0) -> 0 | H9: 1 | I9: 0 | J9: 1 | K9: =IF(OR(J9,G9),1,0) -> 1 | L9: 0 | M9: 0 | N9: 0 | O9: 0 | P9: 1 | Q9: =IF(OR(E9:O9),0,1) -> 0
A10: 209 | B10: Operating surplus: Consumption of fixed capital | C10: w04.a | D10: V_COFC | E10: 0 | F10: 0 | G10: =IF(OR(E10, F10),1,0) -> 0 | H10: 0 | I10: 1 | J10: 1 | K10: =IF(OR(J10,G10),1,0) -> 1 | L10: 0 | M10: 0 | N10: 0 | O10: 0 | P10: 0 | Q10: =IF(OR(E10:O10),0,1) -> 0
A11: 210 | B11: Operating surplus: Rents on land | C11: w04.b | D11: V_RENL | E11: 0 | F11: 0 | G11: =IF(OR(E11, F11),1,0) -> 0 | H11: 0 | I11: 1 | J11: 1 | K11: =IF(OR(J11,G11),1,0) -> 1 | L11: 0 | M11: 0 | N11: 0 | O11: 0 | P11: 0 | Q11: =IF(OR(E11:O11),0,1) -> 0
A12: 211 | B12: Operating surplus: Royalties on resources | C12: w04.c | D12: V_ROYR | E12: 0 | F12: 0 | G12: =IF(OR(E12, F12),1,0) -> 0 | H12: 0 | I12: 1 | J12: 1 | K12: =IF(OR(J12,G12),1,0) -> 1 | L12: 0 | M12: 0 | N12: 0 | O12: 0 | P12: 0 | Q12: =IF(OR(E12:O12),0,1) -> 0
A13: 212 | B13: Operating surplus: Remaining net operating surplus | C13: w04.d | D13: V_NOPS | E13: 0 | F13: 0 | G13: =IF(OR(E13, F13),1,0) -> 0 | H13: 0 | I13: 1 | J13: 1 | K13: =IF(OR(J13,G13),1,0) -> 1 | L13: 0 | M13: 0 | N13: 0 | O13: 0 | P13: 0 | Q13: =IF(OR(E13:O13),0,1) -> 0
... A26: 225 | B26: Capacity utilization (%) | C26: z07 | D26: I_CAPU | E26: 0 | F26: 0 | G26: =IF(OR(E26, F26),1,0) -> 0 | H26: 0 | I26: 0 | J26: 0 | K26: =IF(OR(J26,G26),1,0) -> 0 | L26: 1 | M26: 0 | N26: 0 | O26: 0 | P26: 0 | Q26: =IF(OR(E26:O26),0,1) -> 0
B29: Within CREEA the classification change several times
B30: To compile a consistent classification file appears to be impossible - that's only one of the classifications used in CREEA
B31: Check the specific file in CREEA before using the classification here

Sheet finaldemand
A1: Number | B1: Name | C1: CodeNr | D1: CodeTxt | E1: house | F1: gov | G1: expend | H1: cap | I1: expo | J1: can_be_negative
A2: 164 | B2: Final consumption expenditure by households | C2: y01 | D2: F_HOUS | E2: 1 | F2: 0 | G2: 1 | H2: 0 | I2: 0 | J2: 0
A3: 165 | B3: Final consumption expenditure by non-profit organisations serving households (NPISH) | C3: y02.a | D3: F_NPSH | E3: 0 | F3: 1 | G3: 1 | H3: 0 | I3: 0 | J3: 0
A4: 166 | B4: Final consumption expenditure by government | C4: y02.b | D4: F_GOVE | E4: 0 | F4: 1 | G4: 1 | H4: 0 | I4: 0 | J4: 0
A5: 167 | B5: Gross fixed capital formation | C5: y04 | D5: I_GFCF | E5: 0 | F5: 0 | G5: 0 | H5: 1 | I5: 0 | J5: 1
A6: 168 | B6: Changes in inventories | C6: y05.a | D6: I_CHIN | E6: 0 | F6: 0 | G6: 0 | H6: 1 | I6: 0 | J6: 1
A7: 169 | B7: Changes in valuables | C7: y05.b | D7: I_CHVA | E7: 0 | F7: 0 | G7: 0 | H7: 1 | I7: 0 | J7: 1
A8: 170 | B8: Exports: Total (fob) | C8: y06 | D8: X_TOTA | E8: 0 | F8: 0 | G8: 0 | H8: 0 | I8: 1 | J8: 0

Sheet supply_table_mat
A1: Nr | E1: {=TRANSPOSE(industries!A2:D164)} -> 1 | F1: 2 | G1: 3 | H1: 4 | I1: 5 | J1: 6 | K1: 7 | L1: 8 | M1: 9 | N1: 10 | O1: 11 | P1: 12 | Q1: 13 | R1: 14 | S1: 15 | T1: 16 | U1: 17 | V1: 18 | W1: 19 | X1: 20 | Y1: 21 | Z1: 22 | AA1: 23 | AB1: 24 | AC1: 25 | AD1: 26 | AE1: 27 | AF1: 28 | AG1: 29 | AH1: 30 | AI1: 31 | AJ1: 32 | AK1: 33 | AL1: 34 | AM1: 35 | AN1: 36 | AO1: 37 | AP1: 38 | AQ1: 39 | AR1: 40 | AS1: 41 | AT1: 42 | AU1: 43 | AV1: 44 | AW1: 45 | AX1: 46 | AY1: 47 | AZ1: 48 | BA1: 49 | BB1: 50 | BC1: 51 | BD1: 52 | BE1: 53 | BF1: 54 | BG1: 55 | BH1: 56 | BI1: 57 | BJ1: 58 | BK1: 59 | BL1: 60 | BM1: 61 | BN1: 62 | BO1: 63 | BP1: 64 | BQ1: 65 | BR1: 66 | BS1: 67 | BT1: 68 | BU1: 69 | BV1: 70 | BW1: 71 | BX1: 72 | BY1: 73 | BZ1: 74 | CA1: 75 | CB1: 76 | CC1: 77 | CD1: 78 | CE1: 79 | CF1: 80 | CG1: 81 | CH1: 82 | CI1: 83 | CJ1: 84 | CK1: 85 | CL1: 86 | CM1: 87 | CN1: 88 | CO1: 89 | CP1: 90 | CQ1: 91 | CR1: 92 | CS1: 93 | CT1: 94 | CU1: 95 | CV1: 96 | CW1: 97 | CX1: 98 | CY1: 99 | CZ1: 100 | DA1: 101 | DB1: 102 | DC1: 103 | DD1: 104 | DE1: 105 | DF1: 106 | DG1: 107 | DH1: 108 | DI1: 109 | DJ1: 110 | DK1: 111 | DL1: 112 | DM1: 113 | DN1: 114 | DO1: 115 | DP1: 116 | DQ1: 117 | DR1: 118 | DS1: 119 | DT1: 120 | DU1: 121 | DV1: 122 | DW1: 123 | DX1: 124 | DY1: 125 | DZ1: 126 | EA1: 127 | EB1: 128 | EC1: 129 | ED1: 130 | EE1: 131 | EF1: 132 | EG1: 133 | EH1: 134 | EI1: 135 | EJ1: 136 | EK1: 137 | EL1: 138 | EM1: 139 | EN1: 140 | EO1: 141 | EP1: 142 | EQ1: 143 | ER1: 144 | ES1: 145 | ET1: 146 | EU1: 147 | EV1: 148 | EW1: 149 | EX1: 150 | EY1: 151 | EZ1: 152 | FA1: 153 | FB1: 154 | FC1: 155 | FD1: 156 | FE1: 157 | FF1: 158 | FG1: 159 | FH1: 160 | FI1: 161 | FJ1: 162 | FK1: 163 | FL1: 164
B2: Name | E2: Cultivation of paddy rice | F2: Cultivation of wheat | G2: Cultivation of cereal grains nec | H2: Cultivation of vegetables, fruit, nuts | I2: Cultivation of oil seeds | J2: Cultivation of sugar cane, sugar beet | K2: Cultivation of plant-based fibers | L2: Cultivation of crops nec | M2: Cattle farming | N2: Pigs farming | O2: Poultry farming | P2: Meat animals nec | Q2: Animal products nec | R2: Raw milk | S2: Wool, silk-worm cocoons | T2: Manure treatment (conventional), storage and land application | U2: Manure treatment (biogas), storage and land application | V2: Forestry, logging and related service activities (02) | W2: Fishing, operating of fish hatcheries and fish farms; service activities incidental to fishing (05) | X2: Mining of coal and lignite; extraction of peat (10) | Y2: Extraction of crude petroleum and services related to crude oil extraction, excluding surveying | Z2: Extraction of natural gas and services related to natural gas extraction, excluding surveying | AA2: Extraction, liquefaction, and regasification of other petroleum and gaseous materials | AB2: Mining of uranium and thorium ores (12) | AC2: Mining of iron ores | AD2: Mining of copper ores and concentrates | AE2: Mining of nickel ores and concentrates | AF2: Mining of aluminium ores and concentrates | AG2: Mining of precious metal ores and concentrates | AH2: Mining of lead, zinc and tin ores and concentrates | AI2: Mining of other non-ferrous metal ores and concentrates | AJ2: Quarrying of stone | AK2: Quarrying of sand and clay | AL2: Mining of chemical and fertilizer minerals, production of salt, other mining and quarrying n.e.c. | AM2: Processing of meat cattle | AN2: Processing of meat pigs | AO2: Processing of meat poultry | AP2: Production of meat products nec | AQ2: Processing vegetable oils and fats | AR2: Processing of dairy products | AS2: Processed rice | AT2: Sugar refining | AU2: Processing of Food products nec | AV2: Manufacture of beverages | AW2: Manufacture of fish products | AX2: Manufacture of tobacco products (16) | AY2: Manufacture of textiles (17) | AZ2: Manufacture of wearing apparel; dressing and dyeing of fur (18) | BA2: Tanning and dressing of leather; manufacture of luggage, handbags, saddlery, harness and footwear (19) | BB2: Manufacture of wood and of products of wood and cork, except furniture; manufacture of articles of straw and plaiting materials (20) | BC2: Re-processing of secondary wood material into new wood material | BD2: Pulp | BE2: Re-processing of secondary paper into new pulp | BF2: Paper | BG2: Publishing, printing and reproduction of recorded media (22) | BH2: Manufacture of coke oven products | BI2: Petroleum Refinery | BJ2: Processing of nuclear fuel | BK2: Plastics, basic | BL2: Re-processing of secondary plastic into new plastic | BM2: N-fertiliser | BN2: P- and other fertiliser | BO2: Chemicals nec | BP2: Manufacture of rubber and plastic products (25) | BQ2: Manufacture of glass and glass products | BR2: Re-processing of secondary glass into new glass | BS2: Manufacture of ceramic goods | BT2: Manufacture of bricks, tiles and construction products, in baked clay | BU2: Manufacture of cement, lime and plaster | BV2: Re-processing of ash into clinker | BW2: Manufacture of other non-metallic mineral products n.e.c. | BX2: Manufacture of basic iron and steel and of ferro-alloys and first products thereof | BY2: Re-processing of secondary steel into new steel | BZ2: Precious metals production | CA2: Re-processing of secondary preciuos metals into new preciuos metals | CB2: Aluminium production | CC2: Re-processing of secondary aluminium into new aluminium | CD2: Lead, zinc and tin production | CE2: Re-processing of secondary lead into new lead, zinc and tin | CF2: Copper production | CG2: Re-processing of secondary copper into new copper | CH2: Other non-ferrous metal production | CI2: Re-processing of secondary other non-ferrous metals into new other non-ferrous metals | CJ2: Casting of metals | CK2: Manufacture of fabricated metal products, except machinery and equipment (28) | CL2: Manufacture of machinery and equipment n.e.c. (29) | CM2: Manufacture of office machinery and computers (30) | CN2: Manufacture of electrical machinery and apparatus n.e.c. (31) | CO2: Manufacture of radio, television and communication equipment and apparatus (32) | CP2: Manufacture of medical, precision and optical instruments, watches and clocks (33) | CQ2: Manufacture of motor vehicles, trailers and semi-trailers (34) | CR2: Manufacture of other transport equipment (35) | CS2: Manufacture of furniture; manufacturing n.e.c. (36) | CT2: Recycling of waste and scrap | CU2: Recycling of bottles by direct reuse | CV2: Production of electricity by coal | CW2: Production of electricity by gas | CX2: Production of electricity by nuclear | CY2: Production of electricity by hydro | CZ2: Production of electricity by wind | DA2: Production of electricity by petroleum and other oil derivatives | DB2: Production of electricity by biomass and waste | DC2: Production of electricity by solar photovoltaic | DD2: Production of electricity by solar thermal | DE2: Production of electricity by tide, wave, ocean | DF2: Production of electricity by Geothermal | DG2: Production of electricity nec | DH2: Transmission of electricity | DI2: Distribution and trade of electricity | DJ2: Manufacture of gas; distribution of gaseous fuels through mains | DK2: Steam and hot water supply | DL2: Collection, purification and distribution of water (41) | DM2: Construction (45) | DN2: Re-processing of secondary construction material into aggregates | DO2: Sale, maintenance, repair of motor vehicles, motor vehicles parts, motorcycles, motor cycles parts and accessoiries | DP2: Retail sale of automotive fuel | DQ2: Wholesale trade and commission trade, except of motor vehicles and motorcycles (51) | DR2: Retail trade, except of motor vehicles and motorcycles; repair of personal and household goods (52) | DS2: Hotels and restaurants (55) | DT2: Transport via railways | DU2: Other land transport | DV2: Transport via pipelines | DW2: Sea and coastal water transport | DX2: Inland water transport | DY2: Air transport (62) | DZ2: Supporting and auxiliary transport activities; activities of travel agencies (63) | EA2: Post and telecommunications (64) | EB2: Financial intermediation, except insurance and pension funding (65) | EC2: Insurance and pension funding, except compulsory social security (66) | ED2: Activities auxiliary to financial intermediation (67) | EE2: Real estate activities (70) | EF2: Renting of machinery and equipment without operator and of personal and household goods (71) | EG2: Computer and related activities (72) | EH2: Research and development (73) | EI2: Other business activities (74) | EJ2: Public administration and defence; compulsory social security (75) | EK2: Education (80) | EL2: Health and social work (85) | EM2: Incineration of waste: Food | EN2: Incineration of waste: Paper | EO2: Incineration of waste: Plastic | EP2: Incineration of waste: Metals and Inert materials | EQ2: Incineration of waste: Textiles | ER2: Incineration of waste: Wood | ES2: Incineration of waste: Oil/Hazardous waste | ET2: Biogasification of food waste, incl. land application | EU2: Biogasification of paper, incl. land application | EV2: Biogasification of sewage slugde, incl. land application | EW2: Composting of food waste, incl. land application | EX2: Composting of paper and wood, incl. land application | EY2: Waste water treatment, food | EZ2: Waste water treatment, other | FA2: Landfill of waste: Food | FB2: Landfill of waste: Paper | FC2: Landfill of waste: Plastic | FD2: Landfill of waste: Inert/metal/hazardous | FE2: Landfill of waste: Textiles | FF2: Landfill of waste: Wood | FG2: Activities of membership organisation n.e.c. (91) | FH2: Recreational, cultural and sporting activities (92) | FI2: Other service activities (93) | FJ2: Private households with employed persons (95) | FK2: Extra-territorial organizations and bodies | FL2: Imported Products: Total (cif)
C3: CodeNr | E3: i01.a | F3: i01.b | G3: i01.c | H3: i01.d | I3: i01.e | J3: i01.f | K3: i01.g | L3: i01.h | M3: i01.i | N3: i01.j | O3: i01.k | P3: i01.l | Q3: i01.m | R3: i01.n | S3: i01.o | T3: i01.w.1 | U3: i01.w.2 | V3: i02 | W3: i05 | X3: i10 | Y3: i11.a | Z3: i11.b | AA3: i11.c | AB3: i12 | AC3: i13.1 | AD3: i13.20.11 | AE3: i13.20.12 | AF3: i13.20.13 | AG3: i13.20.14 | AH3: i13.20.15 | AI3: i13.20.16 | AJ3: i14.1 | AK3: i14.2 | AL3: i14.3 | AM3: i15.a | AN3: i15.b | AO3: i15.c | AP3: i15.d | AQ3: i15.e | AR3: i15.f | AS3: i15.g | AT3: i15.h | AU3: i15.i | AV3: i15.j | AW3: i15.k | AX3: i16 | AY3: i17 | AZ3: i18 | BA3: i19 | BB3: i20 | BC3: i20.w | BD3: i21.1 | BE3: i21.w.1 | BF3: i21.2 | BG3: i22 | BH3: i23.1 | BI3: i23.2 | BJ3: i23.3 | BK3: i24.a | BL3: i24.a.w | BM3: i24.b | BN3: i24.c | BO3: i24.d | BP3: i25 | BQ3: i26.a | BR3: i26.a.w | BS3: i26.b | BT3: i26.c | BU3: i26.d | BV3: i26.d.w | BW3: i26.e | BX3: i27.a | BY3: i27.a.w | BZ3: i27.41 | CA3: i27.41.w | CB3: i27.42 | CC3: i27.42.w | CD3: i27.43 | CE3: i27.43.w | CF3: i27.44 | CG3: i27.44.w | CH3: i27.45 | CI3: i27.45.w | CJ3: i27.5 | CK3: i28 | CL3: i29 | CM3: i30 | CN3: i31 | CO3: i32 | CP3: i33 | CQ3: i34 | CR3: i35 | CS3: i36 | CT3: i37 | CU3: i37.w.1 | CV3: i40.11.a | CW3: i40.11.b | CX3: i40.11.c | CY3: i40.11.d | CZ3: i40.11.e | DA3: i40.11.f | DB3: i40.11.g | DC3: i40.11.h | DD3: i40.11.i | DE3: i40.11.j | DF3: i40.11.k | DG3: i40.11.l | DH3: i40.12 | DI3: i40.13 | DJ3: i40.2 | DK3: i40.3 | DL3: i41 | DM3: i45 | DN3: i45.w | DO3: i50.a | DP3: i50.b | DQ3: i51 | DR3: i52 | DS3: i55 | DT3: i60.1 | DU3: i60.2 | DV3: i60.3 | DW3: i61.1 | DX3: i61.2 | DY3: i62 | DZ3: i63 | EA3: i64 | EB3: i65 | EC3: i66 | ED3: i67 | EE3: i70 | EF3: i71 | EG3: i72 | EH3: i73 | EI3: i74 | EJ3: i75 | EK3: i80 | EL3: i85 | EM3: i90.1.a | EN3: i90.1.b | EO3: i90.1.c | EP3: i90.1.d | EQ3: i90.1.e | ER3: i90.1.f | ES3: i90.1.g | ET3: i90.2.a | EU3: i90.2.b | EV3: i90.2.c | EW3: i90.3.a | EX3: i90.3.b | EY3: i90.4.a | EZ3: i90.4.b | FA3: i90.5.a | FB3: i90.5.b | FC3: i90.5.c | FD3: i90.5.d | FE3: i90.5.e | FF3: i90.5.f | FG3: i91 | FH3: i92 | FI3: i93 | FJ3: i95 | FK3: i99 | FL3: m01
D4: CodeTxt | E4: A_PARI | F4: A_WHEA | G4: A_OCER | H4: A_FVEG | I4: A_OILS | J4: A_SUGB | K4: A_FIBR | L4: A_OTCR | M4: A_CATL | N4: A_PIGS | O4: A_PLTR | P4: A_OMEA | Q4: A_OANP | R4: A_MILK | S4: A_WOOL | T4: A_MANC | U4: A_MANB | V4: A_FORE | W4: A_FISH | X4: A_COAL | Y4: A_COIL | Z4: A_GASE | AA4: A_OGPL | AB4: A_ORAN | AC4: A_IRON | AD4: A_COPO | AE4: A_NIKO | AF4: A_ALUO | AG4: A_PREO | AH4: A_LZTO | AI4: A_ONFO | AJ4: A_STON | AK4: A_SDCL | AL4: A_CHMF | AM4: A_PCAT | AN4: A_PPIG | AO4: A_PPLT | AP4: A_POME | AQ4: A_VOIL | AR4: A_DAIR | AS4: A_RICE | AT4: A_SUGR | AU4: A_OFOD | AV4: A_BEVR | AW4: A_FSHP | AX4: A_TOBC | AY4: A_TEXT | AZ4: A_GARM | BA4: A_LETH | BB4: A_WOOD | BC4: A_WOOW | BD4: A_PULP | BE4: A_PAPR | BF4: A_PAPE | BG4: A_MDIA | BH4: A_COKE | BI4: A_REFN | BJ4: A_NUCF | BK4: A_PLAS | BL4: A_PLAW | BM4: A_NFER | BN4: A_PFER | BO4: A_CHEM | BP4: A_RUBP | BQ4: A_GLAS | BR4: A_GLAW | BS4: A_CRMC | BT4: A_BRIK | BU4: A_CMNT | BV4: A_ASHW | BW4: A_ONMM | BX4: A_STEL | BY4: A_STEW | BZ4: A_PREM | CA4: A_PREW | CB4: A_ALUM | CC4: A_ALUW | CD4: A_LZTP | CE4: A_LZTW | CF4: A_COPP | CG4: A_COPW | CH4: A_ONFM | CI4: A_ONFW | CJ4: A_METC | CK4: A_FABM | CL4: A_MACH | CM4: A_OFMA | CN4: A_ELMA | CO4: A_RATV | CP4: A_MEIN | CQ4: A_MOTO | CR4: A_OTRE | CS4: A_FURN | CT4: A_RYMS | CU4: A_BOTW | CV4: A_POWC | CW4: A_POWG | CX4: A_POWN | CY4: A_POWH | CZ4: A_POWW | DA4: A_POWP | DB4: A_POWB | DC4: A_POWS | DD4: A_POWE | DE4: A_POWO | DF4: A_POWM | DG4: A_POWZ | DH4: A_POWT | DI4: A_POWD | DJ4: A_GASD | DK4: A_HWAT | DL4: A_WATR | DM4: A_CONS | DN4: A_CONW | DO4: A_TDMO | DP4: A_TDFU | DQ4: A_TDWH | DR4: A_TDRT | DS4: A_HORE | DT4: A_TRAI | DU4: A_TLND | DV4: A_TPIP | DW4: A_TWAS | DX4: A_TWAI | DY4: A_TAIR | DZ4: A_TAUX | EA4: A_PTEL | EB4: A_FINT | EC4: A_FINS | ED4: A_FAUX | EE4: A_REAL | EF4: A_MARE | EG4: A_COMP | EH4: A_RESD | EI4: A_OBUS | EJ4: A_PADF | EK4: A_EDUC | EL4: A_HEAL | EM4: A_INCF | EN4: A_INCP | EO4: A_INCL | EP4: A_INCM | EQ4: A_INCT | ER4: A_INCW | ES4: A_INCO | ET4: A_BIOF | EU4: A_BIOP | EV4: A_BIOS | EW4: A_COMF | EX4: A_COMW | EY4: A_WASF | EZ4: A_WASO | FA4: A_LANF | FB4: A_LANP | FC4: A_LANL | FD4: A_LANI | FE4: A_LANT | FF4: A_LANW | FG4: A_ORGA | FH4: A_RECR | FI4: A_OSER | FJ4: A_PRHH | FK4: A_EXTO | FL4: M_TOTA
A5: =products!A2 -> 1 | B5: =products!B2 -> Paddy rice | C5: =products!C2 -> p01.a | D5: =products!D2 -> C_PARI
A6: =products!A3 -> 2 | B6: =products!B3 -> Wheat | C6: =products!C3 -> p01.b | D6: =products!D3 -> C_WHEA
A7: =products!A4 -> 3 | B7: =products!B4 -> Cereal grains nec | C7: =products!C4 -> p01.c | D7: =products!D4 -> C_OCER
A8: =products!A5 -> 4 | B8: =products!B5 -> Vegetables, fruit, nuts | C8: =products!C5 -> p01.d | D8: =products!D5 -> C_FVEG
A9: =products!A6 -> 5 | B9: =products!B6 -> Oil seeds | C9: =products!C6 -> p01.e | D9: =products!D6 -> C_OILS
A10: =products!A7 -> 6 | B10: =products!B7 -> Sugar cane, sugar beet | C10: =products!C7 -> p01.f | D10: =products!D7 -> C_SUGB
A11: =products!A8 -> 7 | B11: =products!B8 -> Plant-based fibers | C11: =products!C8 -> p01.g | D11: =products!D8 -> C_FIBR
A12: =products!A9 -> 8 | B12: =products!B9 -> Crops nec | C12: =products!C9 -> p01.h | D12: =products!D9 -> C_OTCR
A13: =products!A10 -> 9 | B13: =products!B10 -> Cattle | C13: =products!C10 -> p01.i | D13: =products!D10 -> C_CATL
A14: =products!A11 -> 10 | B14: =products!B11 -> Pigs | C14: =products!C11 -> p01.j | D14: =products!D11 -> C_PIGS
A15: =products!A12 -> 11 | B15: =products!B12 -> Poultry | C15: =products!C12 -> p01.k | D15: =products!D12 -> C_PLTR
A16: =products!A13 -> 12 | B16: =products!B13 -> Meat animals nec | C16: =products!C13 -> p01.l | D16: =products!D13 -> C_OMEA
... A204: =products!A201 -> 200 | B204: =products!B201 -> Extra-territorial organizations and bodies | C204: =products!C201 -> p99 | D204: =products!D201 -> C_EXTO

Sheet use_table_mat
A1: Nr | E1: {=TRANSPOSE(industries!A2:D164)} -> 1 | F1: 2 | G1: 3 | H1: 4 | I1: 5 | J1: 6 | K1: 7 | L1: 8 | M1: 9 | N1: 10 | O1: 11 | P1: 12 | Q1: 13 | R1: 14 | S1: 15 | T1: 16 | U1: 17 | V1: 18 | W1: 19 | X1: 20 | Y1: 21 | Z1: 22 | AA1: 23 | AB1: 24 | AC1: 25 | AD1: 26 | AE1: 27 | AF1: 28 | AG1: 29 | AH1: 30 | AI1: 31 | AJ1: 32 | AK1: 33 | AL1: 34 | AM1: 35 | AN1: 36 | AO1: 37 | AP1: 38 | AQ1: 39 | AR1: 40 | AS1: 41 | AT1: 42 | AU1: 43 | AV1: 44 | AW1: 45 | AX1: 46 | AY1: 47 | AZ1: 48 | BA1: 49 | BB1: 50 | BC1: 51 | BD1: 52 | BE1: 53 | BF1: 54 | BG1: 55 | BH1: 56 | BI1: 57 | BJ1: 58 | BK1: 59 | BL1: 60 | BM1: 61 | BN1: 62 | BO1: 63 | BP1: 64 | BQ1: 65 | BR1: 66 | BS1: 67 | BT1: 68 | BU1: 69 | BV1: 70 | BW1: 71 | BX1: 72 | BY1: 73 | BZ1: 74 | CA1: 75 | CB1: 76 | CC1: 77 | CD1: 78 | CE1: 79 | CF1: 80 | CG1: 81 | CH1: 82 | CI1: 83 | CJ1: 84 | CK1: 85 | CL1: 86 | CM1: 87 | CN1: 88 | CO1: 89 | CP1: 90 | CQ1: 91 | CR1: 92 | CS1: 93 | CT1: 94 | CU1: 95 | CV1: 96 | CW1: 97 | CX1: 98 | CY1: 99 | CZ1: 100 | DA1: 101 | DB1: 102 | DC1: 103 | DD1: 104 | DE1: 105 | DF1: 106 | DG1: 107 | DH1: 108 | DI1: 109 | DJ1: 110 | DK1: 111 | DL1: 112 | DM1: 113 | DN1: 114 | DO1: 115 | DP1: 116 | DQ1: 117 | DR1: 118 | DS1: 119 | DT1: 120 | DU1: 121 | DV1: 122 | DW1: 123 | DX1: 124 | DY1: 125 | DZ1: 126 | EA1: 127 | EB1: 128 | EC1: 129 | ED1: 130 | EE1: 131 | EF1: 132 | EG1: 133 | EH1: 134 | EI1: 135 | EJ1: 136 | EK1: 137 | EL1: 138 | EM1: 139 | EN1: 140 | EO1: 141 | EP1: 142 | EQ1: 143 | ER1: 144 | ES1: 145 | ET1: 146 | EU1: 147 | EV1: 148 | EW1: 149 | EX1: 150 | EY1: 151 | EZ1: 152 | FA1: 153 | FB1: 154 | FC1: 155 | FD1: 156 | FE1: 157 | FF1: 158 | FG1: 159 | FH1: 160 | FI1: 161 | FJ1: 162 | FK1: 163 | FL1: {=TRANSPOSE(finaldemand!A2:D8)} -> 164 | FM1: 165 | FN1: 166 | FO1: 167 | FP1: 168 | FQ1: 169 | FR1: 170
B2: Name | E2: Cultivation of paddy rice | F2: Cultivation of wheat | G2: Cultivation of cereal grains nec | H2: Cultivation of vegetables, fruit, nuts | I2: Cultivation of oil seeds | J2: Cultivation of sugar cane, sugar beet | K2: Cultivation of plant-based fibers | L2: Cultivation of crops nec | M2: Cattle farming | N2: Pigs farming | O2: Poultry farming | P2: Meat animals nec | Q2: Animal products nec | R2: Raw milk | S2: Wool, silk-worm cocoons | T2: Manure treatment (conventional), storage and land application | U2: Manure treatment (biogas), storage and land application | V2: Forestry, logging and related service activities (02) | W2: Fishing, operating of fish hatcheries and fish farms; service activities incidental to fishing (05) | X2: Mining of coal and lignite; extraction of peat (10) | Y2: Extraction of crude petroleum and services related to crude oil extraction, excluding surveying | Z2: Extraction of natural gas and services related to natural gas extraction, excluding surveying | AA2: Extraction, liquefaction, and regasification of other petroleum and gaseous materials | AB2: Mining of uranium and thorium ores (12) | AC2: Mining of iron ores | AD2: Mining of copper ores and concentrates | AE2: Mining of nickel ores and concentrates | AF2: Mining of aluminium ores and concentrates | AG2: Mining of precious metal ores and concentrates | AH2: Mining of lead, zinc and tin ores and concentrates | AI2: Mining of other non-ferrous metal ores and concentrates | AJ2: Quarrying of stone | AK2: Quarrying of sand and clay | AL2: Mining of chemical and fertilizer minerals, production of salt, other mining and quarrying n.e.c. | AM2: Processing of meat cattle | AN2: Processing of meat pigs | AO2: Processing of meat poultry | AP2: Production of meat products nec | AQ2: Processing vegetable oils and fats | AR2: Processing of dairy products | AS2: Processed rice | AT2: Sugar refining | AU2: Processing of Food products nec | AV2: Manufacture of beverages | AW2: Manufacture of fish products | AX2: Manufacture of tobacco products (16) | AY2: Manufacture of textiles (17) | AZ2: Manufacture of wearing apparel; dressing and dyeing of fur (18) | BA2: Tanning and dressing of leather; manufacture of luggage, handbags, saddlery, harness and footwear (19) | BB2: Manufacture of wood and of products of wood and cork, except furniture; manufacture of articles of straw and plaiting materials (20) | BC2: Re-processing of secondary wood material into new wood material | BD2: Pulp | BE2: Re-processing of secondary paper into new pulp | BF2: Paper | BG2: Publishing, printing and reproduction of recorded media (22) | BH2: Manufacture of coke oven products | BI2: Petroleum Refinery | BJ2: Processing of nuclear fuel | BK2: Plastics, basic | BL2: Re-processing of secondary plastic into new plastic | BM2: N-fertiliser | BN2: P- and other fertiliser | BO2: Chemicals nec | BP2: Manufacture of rubber and plastic products (25) | BQ2: Manufacture of glass and glass products | BR2: Re-processing of secondary glass into new glass | BS2: Manufacture of ceramic goods | BT2: Manufacture of bricks, tiles and construction products, in baked clay | BU2: Manufacture of cement, lime and plaster | BV2: Re-processing of ash into clinker | BW2: Manufacture of other non-metallic mineral products n.e.c. | BX2: Manufacture of basic iron and steel and of ferro-alloys and first products thereof | BY2: Re-processing of secondary steel into new steel | BZ2: Precious metals production | CA2: Re-processing of secondary preciuos metals into new preciuos metals | CB2: Aluminium production | CC2: Re-processing of secondary aluminium into new aluminium | CD2: Lead, zinc and tin production | CE2: Re-processing of secondary lead into new lead, zinc and tin | CF2: Copper production | CG2: Re-processing of secondary copper into new copper | CH2: Other non-ferrous metal production | CI2: Re-processing of secondary other non-ferrous metals into new other non-ferrous metals | CJ2: Casting of metals | CK2: Manufacture of fabricated metal products, except machinery and equipment (28) | CL2: Manufacture of machinery and equipment n.e.c. (29) | CM2: Manufacture of office machinery and computers (30) | CN2: Manufacture of electrical machinery and apparatus n.e.c. (31) | CO2: Manufacture of radio, television and communication equipment and apparatus (32) | CP2: Manufacture of medical, precision and optical instruments, watches and clocks (33) | CQ2: Manufacture of motor vehicles, trailers and semi-trailers (34) | CR2: Manufacture of other transport equipment (35) | CS2: Manufacture of furniture; manufacturing n.e.c. (36) | CT2: Recycling of waste and scrap | CU2: Recycling of bottles by direct reuse | CV2: Production of electricity by coal | CW2: Production of electricity by gas | CX2: Production of electricity by nuclear | CY2: Production of electricity by hydro | CZ2: Production of electricity by wind | DA2: Production of electricity by petroleum and other oil derivatives | DB2: Production of electricity by biomass and waste | DC2: Production of electricity by solar photovoltaic | DD2: Production of electricity by solar thermal | DE2: Production of electricity by tide, wave, ocean | DF2: Production of electricity by Geothermal | DG2: Production of electricity nec | DH2: Transmission of electricity | DI2: Distribution and trade of electricity | DJ2: Manufacture of gas; distribution of gaseous fuels through mains | DK2: Steam and hot water supply | DL2: Collection, purification and distribution of water (41) | DM2: Construction (45) | DN2: Re-processing of secondary construction material into aggregates | DO2: Sale, maintenance, repair of motor vehicles, motor vehicles parts, motorcycles, motor cycles parts and accessoiries | DP2: Retail sale of automotive fuel | DQ2: Wholesale trade and commission trade, except of motor vehicles and motorcycles (51) | DR2: Retail trade, except of motor vehicles and motorcycles; repair of personal and household goods (52) | DS2: Hotels and restaurants (55) | DT2: Transport via railways | DU2: Other land transport | DV2: Transport via pipelines | DW2: Sea and coastal water transport | DX2: Inland water transport | DY2: Air transport (62) | DZ2: Supporting and auxiliary transport activities; activities of travel agencies (63) | EA2: Post and telecommunications (64) | EB2: Financial intermediation, except insurance and pension funding (65) | EC2: Insurance and pension funding, except compulsory social security (66) | ED2: Activities auxiliary to financial intermediation (67) | EE2: Real estate activities (70) | EF2: Renting of machinery and equipment without operator and of personal and household goods (71) | EG2: Computer and related activities (72) | EH2: Research and development (73) | EI2: Other business activities (74) | EJ2: Public administration and defence; compulsory social security (75) | EK2: Education (80) | EL2: Health and social work (85) | EM2: Incineration of waste: Food | EN2: Incineration of waste: Paper | EO2: Incineration of waste: Plastic | EP2: Incineration of waste: Metals and Inert materials | EQ2: Incineration of waste: Textiles | ER2: Incineration of waste: Wood | ES2: Incineration of waste: Oil/Hazardous waste | ET2: Biogasification of food waste, incl. land application | EU2: Biogasification of paper, incl. land application | EV2: Biogasification of sewage slugde, incl. land application | EW2: Composting of food waste, incl. land application | EX2: Composting of paper and wood, incl. land application | EY2: Waste water treatment, food | EZ2: Waste water treatment, other | FA2: Landfill of waste: Food | FB2: Landfill of waste: Paper | FC2: Landfill of waste: Plastic | FD2: Landfill of waste: Inert/metal/hazardous | FE2: Landfill of waste: Textiles | FF2: Landfill of waste: Wood | FG2: Activities of membership organisation n.e.c. (91) | FH2: Recreational, cultural and sporting activities (92) | FI2: Other service activities (93) | FJ2: Private households with employed persons (95) | FK2: Extra-territorial organizations and bodies | FL2: Final consumption expenditure by households | FM2: Final consumption expenditure by non-profit organisations serving households (NPISH) | FN2: Final consumption expenditure by government | FO2: Gross fixed capital formation | FP2: Changes in inventories | FQ2: Changes in valuables | FR2: Exports: Total (fob)
C3: CodeNr | E3: i01.a | F3: i01.b | G3: i01.c | H3: i01.d | I3: i01.e | J3: i01.f | K3: i01.g | L3: i01.h | M3: i01.i | N3: i01.j | O3: i01.k | P3: i01.l | Q3: i01.m | R3: i01.n | S3: i01.o | T3: i01.w.1 | U3: i01.w.2 | V3: i02 | W3: i05 | X3: i10 | Y3: i11.a | Z3: i11.b | AA3: i11.c | AB3: i12 | AC3: i13.1 | AD3: i13.20.11 | AE3: i13.20.12 | AF3: i13.20.13 | AG3: i13.20.14 | AH3: i13.20.15 | AI3: i13.20.16 | AJ3: i14.1 | AK3: i14.2 | AL3: i14.3 | AM3: i15.a | AN3: i15.b | AO3: i15.c | AP3: i15.d | AQ3: i15.e | AR3: i15.f | AS3: i15.g | AT3: i15.h | AU3: i15.i | AV3: i15.j | AW3: i15.k | AX3: i16 | AY3: i17 | AZ3: i18 | BA3: i19 | BB3: i20 | BC3: i20.w | BD3: i21.1 | BE3: i21.w.1 | BF3: i21.2 | BG3: i22 | BH3: i23.1 | BI3: i23.2 | BJ3: i23.3 | BK3: i24.a | BL3: i24.a.w | BM3: i24.b | BN3: i24.c | BO3: i24.d | BP3: i25 | BQ3: i26.a | BR3: i26.a.w | BS3: i26.b | BT3: i26.c | BU3: i26.d | BV3: i26.d.w | BW3: i26.e | BX3: i27.a | BY3: i27.a.w | BZ3: i27.41 | CA3: i27.41.w | CB3: i27.42 | CC3: i27.42.w | CD3: i27.43 | CE3: i27.43.w | CF3: i27.44 | CG3: i27.44.w | CH3: i27.45 | CI3: i27.45.w | CJ3: i27.5 | CK3: i28 | CL3: i29 | CM3: i30 | CN3: i31 | CO3: i32 | CP3: i33 | CQ3: i34 | CR3: i35 | CS3: i36 | CT3: i37 | CU3: i37.w.1 | CV3: i40.11.a | CW3: i40.11.b | CX3: i40.11.c | CY3: i40.11.d | CZ3: i40.11.e | DA3: i40.11.f | DB3: i40.11.g | DC3: i40.11.h | DD3: i40.11.i | DE3: i40.11.j | DF3: i40.11.k | DG3: i40.11.l | DH3: i40.12 | DI3: i40.13 | DJ3: i40.2 | DK3: i40.3 | DL3: i41 | DM3: i45 | DN3: i45.w | DO3: i50.a | DP3: i50.b | DQ3: i51 | DR3: i52 | DS3: i55 | DT3: i60.1 | DU3: i60.2 | DV3: i60.3 | DW3: i61.1 | DX3: i61.2 | DY3: i62 | DZ3: i63 | EA3: i64 | EB3: i65 | EC3: i66 | ED3: i67 | EE3: i70 | EF3: i71 | EG3: i72 | EH3: i73 | EI3: i74 | EJ3: i75 | EK3: i80 | EL3: i85 | EM3: i90.1.a | EN3: i90.1.b | EO3: i90.1.c | EP3: i90.1.d | EQ3: i90.1.e | ER3: i90.1.f | ES3: i90.1.g | ET3: i90.2.a | EU3: i90.2.b | EV3: i90.2.c | EW3: i90.3.a | EX3: i90.3.b | EY3: i90.4.a | EZ3: i90.4.b | FA3: i90.5.a | FB3: i90.5.b | FC3: i90.5.c | FD3: i90.5.d | FE3: i90.5.e | FF3: i90.5.f | FG3: i91 | FH3: i92 | FI3: i93 | FJ3: i95 | FK3: i99 | FL3: y01 | FM3: y02.a | FN3: y02.b | FO3: y04 | FP3: y05.a | FQ3: y05.b | FR3: y06
D4: CodeTxt | E4: A_PARI | F4: A_WHEA | G4: A_OCER | H4: A_FVEG | I4: A_OILS | J4: A_SUGB | K4: A_FIBR | L4: A_OTCR | M4: A_CATL | N4: A_PIGS | O4: A_PLTR | P4: A_OMEA | Q4: A_OANP | R4: A_MILK | S4: A_WOOL | T4: A_MANC | U4: A_MANB | V4: A_FORE | W4: A_FISH | X4: A_COAL | Y4: A_COIL | Z4: A_GASE | AA4: A_OGPL | AB4: A_ORAN | AC4: A_IRON | AD4: A_COPO | AE4: A_NIKO | AF4: A_ALUO | AG4: A_PREO | AH4: A_LZTO | AI4: A_ONFO | AJ4: A_STON | AK4: A_SDCL | AL4: A_CHMF | AM4: A_PCAT | AN4: A_PPIG | AO4: A_PPLT | AP4: A_POME | AQ4: A_VOIL | AR4: A_DAIR | AS4: A_RICE | AT4: A_SUGR | AU4: A_OFOD | AV4: A_BEVR | AW4: A_FSHP | AX4: A_TOBC | AY4: A_TEXT | AZ4: A_GARM | BA4: A_LETH | BB4: A_WOOD | BC4: A_WOOW | BD4: A_PULP | BE4: A_PAPR | BF4: A_PAPE | BG4: A_MDIA | BH4: A_COKE | BI4: A_REFN | BJ4: A_NUCF | BK4: A_PLAS | BL4: A_PLAW | BM4: A_NFER | BN4: A_PFER | BO4: A_CHEM | BP4: A_RUBP | BQ4: A_GLAS | BR4: A_GLAW | BS4: A_CRMC | BT4: A_BRIK | BU4: A_CMNT | BV4: A_ASHW | BW4: A_ONMM | BX4: A_STEL | BY4: A_STEW | BZ4: A_PREM | CA4: A_PREW | CB4: A_ALUM | CC4: A_ALUW | CD4: A_LZTP | CE4: A_LZTW | CF4: A_COPP | CG4: A_COPW | CH4: A_ONFM | CI4: A_ONFW | CJ4: A_METC | CK4: A_FABM | CL4: A_MACH | CM4: A_OFMA | CN4: A_ELMA | CO4: A_RATV | CP4: A_MEIN | CQ4: A_MOTO | CR4: A_OTRE | CS4: A_FURN | CT4: A_RYMS | CU4: A_BOTW | CV4: A_POWC | CW4: A_POWG | CX4: A_POWN | CY4: A_POWH | CZ4: A_POWW | DA4: A_POWP | DB4: A_POWB | DC4: A_POWS | DD4: A_POWE | DE4: A_POWO | DF4: A_POWM | DG4: A_POWZ | DH4: A_POWT | DI4: A_POWD | DJ4: A_GASD | DK4: A_HWAT | DL4: A_WATR | DM4: A_CONS | DN4: A_CONW | DO4: A_TDMO | DP4: A_TDFU | DQ4: A_TDWH | DR4: A_TDRT | DS4: A_HORE | DT4: A_TRAI | DU4: A_TLND | DV4: A_TPIP | DW4: A_TWAS | DX4: A_TWAI | DY4: A_TAIR | DZ4: A_TAUX | EA4: A_PTEL | EB4: A_FINT | EC4: A_FINS | ED4: A_FAUX | EE4: A_REAL | EF4: A_MARE | EG4: A_COMP | EH4: A_RESD | EI4: A_OBUS | EJ4: A_PADF | EK4: A_EDUC | EL4: A_HEAL | EM4: A_INCF | EN4: A_INCP | EO4: A_INCL | EP4: A_INCM | EQ4: A_INCT | ER4: A_INCW | ES4: A_INCO | ET4: A_BIOF | EU4: A_BIOP | EV4: A_BIOS | EW4: A_COMF | EX4: A_COMW | EY4: A_WASF | EZ4: A_WASO | FA4: A_LANF | FB4: A_LANP | FC4: A_LANL | FD4: A_LANI | FE4: A_LANT | FF4: A_LANW | FG4: A_ORGA | FH4: A_RECR | FI4: A_OSER | FJ4: A_PRHH | FK4: A_EXTO | FL4: F_HOUS | FM4: F_NPSH | FN4: F_GOVE | FO4: I_GFCF | FP4: I_CHIN | FQ4: I_CHVA | FR4: X_TOTA
A5: =products!A2 -> 1 | B5: =products!B2 -> Paddy rice | C5: =products!C2 -> p01.a | D5: =products!D2 -> C_PARI
A6: =products!A3 -> 2 | B6: =products!B3 -> Wheat | C6: =products!C3 -> p01.b | D6: =products!D3 -> C_WHEA
A7: =products!A4 -> 3 | B7: =products!B4 -> Cereal grains nec | C7: =products!C4 -> p01.c | D7: =products!D4 -> C_OCER
A8: =products!A5 -> 4 | B8: =products!B5 -> Vegetables, fruit, nuts | C8: =products!C5 -> p01.d | D8: =products!D5 -> C_FVEG
A9: =products!A6 -> 5 | B9: =products!B6 -> Oil seeds | C9: =products!C6 -> p01.e | D9: =products!D6 -> C_OILS
A10: =products!A7 -> 6 | B10: =products!B7 -> Sugar cane, sugar beet | C10: =products!C7 -> p01.f | D10: =products!D7 -> C_SUGB
A11: =products!A8 -> 7 | B11: =products!B8 -> Plant-based fibers | C11: =products!C8 -> p01.g | D11: =products!D8 -> C_FIBR
A12: =products!A9 -> 8 | B12: =products!B9 -> Crops nec | C12: =products!C9 -> p01.h | D12: =products!D9 -> C_OTCR
A13: =products!A10 -> 9 | B13: =products!B10 -> Cattle | C13: =products!C10 -> p01.i | D13: =products!D10 -> C_CATL
A14: =products!A11 -> 10 | B14: =products!B11 -> Pigs | C14: =products!C11 -> p01.j | D14: =products!D11 -> C_PIGS
A15: =products!A12 -> 11 | B15: =products!B12 -> Poultry | C15: =products!C12 -> p01.k | D15: =products!D12 -> C_PLTR
A16: =products!A13 -> 12 | B16: =products!B13 -> Meat animals nec | C16: =products!C13 -> p01.l | D16: =products!D13 -> C_OMEA
... A204: =products!A201 -> 200 | B204: =products!B201 -> Extra-territorial organizations and bodies | C204: =products!C201 -> p99 | D204: =products!D201 -> C_EXTO
A205: =valueadded_mat!A2 -> 201 | B205: =valueadded_mat!B2 -> Taxes less subsidies on products purchased: Total | C205: =valueadded_mat!C2 -> w01 | D205: =valueadded_mat!D2 -> T_TLSA
A206: =valueadded_mat!A3 -> 202 | B206: =valueadded_mat!B3 -> Taxes on products purchased | C206: =valueadded_mat!C3 -> w01.a | D206: =valueadded_mat!D3 -> T_TAXA
A207: =valueadded_mat!A4 -> 203 | B207: =valueadded_mat!B4 -> Subsidies on products purchased | C207: =valueadded_mat!C4 -> w01.b | D207: =valueadded_mat!D4 -> T_SUBA
A208: =valueadded_mat!A5 -> 204 | B208: =valueadded_mat!B5 -> Other net taxes on production | C208: =valueadded_mat!C5 -> w02 | D208: =valueadded_mat!D5 -> V_ONTP
A209: =valueadded_mat!A6 -> 205 | B209: =valueadded_mat!B6 -> Compensation of employees; wages, salaries, & employers' social contributions: Total | C209: =valueadded_mat!C6 -> w03 | D209: =valueadded_mat!D6 -> V_WAGE
A210: =valueadded_mat!A7 -> 206 | B210: =valueadded_mat!B7 -> Compensation of employees; wages, salaries, & employers' social contributions: Low-skilled | C210: =valueadded_mat!C7 -> w03.a | D210: =valueadded_mat!D7 -> V_WALS
A211: =valueadded_mat!A8 -> 207 | B211: =valueadded_mat!B8 -> Compensation of employees; wages, salaries, & employers' social contributions: Medium-skilled | C211: =valueadded_mat!C8 -> w03.b | D211: =valueadded_mat!D8 -> V_WAMS
A212: =valueadded_mat!A9 -> 208 | B212: =valueadded_mat!B9 -> Compensation of employees; wages, salaries, & employers' social contributions: High-skilled | C212: =valueadded_mat!C9 -> w03.c | D212: =valueadded_mat!D9 -> V_WAHS
A213: =valueadded_mat!A10 -> 209 | B213: =valueadded_mat!B10 -> Operating surplus: Consumption of fixed capital | C213: =valueadded_mat!C10 -> w04.a | D213: =valueadded_mat!D10 -> V_COFC
A214: =valueadded_mat!A11 -> 210 | B214: =valueadded_mat!B11 -> Operating surplus: Rents on land | C214: =valueadded_mat!C11 -> w04.b | D214: =valueadded_mat!D11 -> V_RENL
A215: =valueadded_mat!A12 -> 211 | B215: =valueadded_mat!B12 -> Operating surplus: Royalties on resources | C215: =valueadded_mat!C12 -> w04.c | D215: =valueadded_mat!D12 -> V_ROYR
A216: =valueadded_mat!A13 -> 212 | B216: =valueadded_mat!B13 -> Operating surplus: Remaining net operating surplus | C216: =valueadded_mat!C13 -> w04.d | D216: =valueadded_mat!D13 -> V_NOPS

Sheet use_layers_mat
A1: Layer | B1: Name | C1: NameShort | D1: Content | E1: bp | F1: marg | G1: tax
A2: 1 | B2: bpdom | C2: ubpd | D2: Domestic use in basic prices | E2: 1 | F2: 0 | G2: 0
A3: 2 | B3: bpimp | C3: ubpi | D3: Use of imported products in basic prices | E3: 1 | F3: 0 | G3: 0
A4: 3 | B4: trade_margins | C4: td | D4: Trade margins | E4: 0 | F4: 1 | G4: 0
A5: 4 | B5: transport_margins | C5: ts | D5: Transport margins | E5: 0 | F5: 1 | G5: 0
A6: 5 | B6: product_taxes | C6: protax | D6: Product taxes | E6: 0 | F6: 0 | G6: 1

Sheet timeline
A1: Number | B1: Years | C1: special | D1: nowcast
A2: 1 | B2: 1995 | C2: start | D2: =FALSE() -> FALSE
A3: 2 | B3: 1996 | D3: =FALSE() -> FALSE
A4: 3 | B4: 1997 | D4: =FALSE() -> FALSE
A5: 4 | B5: 1998 | D5: =FALSE() -> FALSE
A6: 5 | B6: 1999 | D6: =FALSE() -> FALSE
A7: 6 | B7: 2000 | C7: EXIOPOL | D7: =FALSE() -> FALSE
A8: 7 | B8: 2001 | D8: =FALSE() -> FALSE
A9: 8 | B9: 2002 | D9: =FALSE() -> FALSE
A10: 9 | B10: 2003 | D10: =FALSE() -> FALSE
A11: 10 | B11: 2004 | D11: =FALSE() -> FALSE
A12: 11 | B12: 2005 | D12: =FALSE() -> FALSE
A13: 12 | B13: 2006 | D13: =FALSE() -> FALSE
A14: 13 | B14: 2007 | C14: CREEA | D14: =FALSE() -> FALSE
A15: 14 | B15: 2008 | D15: =FALSE() -> FALSE
A16: 15 | B16: 2009 | D16: =FALSE() -> FALSE
A17: 16 | B17: 2010 | D17: =FALSE() -> FALSE
A18: 17 | B18: 2011 | D18: =FALSE() -> FALSE
A19: 18 | B19: 2012 | D19: =FALSE() -> FALSE
A20: 19 | B20: 2013 | D20: =FALSE() -> FALSE
A21: 20 | B21: 2014 | D21: =FALSE() -> FALSE
A22: 21 | B22: 2015 | D22: =FALSE() -> FALSE
A23: 22 | B23: 2016 | D23: =FALSE() -> FALSE
A24: 23 | B24: 2017 | D24: =FALSE() -> FALSE
A25: 24 | B25: 2018 | D25: =FALSE() -> FALSE
A26: 25 | B26: 2019 | D26: =FALSE() -> FALSE
... A29: 28 | B29: 2022 | D29: =FALSE() -> FALSE
A30: 29 | B30: 2023 | C30: end | D30: =FALSE() -> FALSE
A31: 30 | B31: 2024 | D31: =TRUE() -> TRUE
A32: 31 | B32: 2025 | D32: =TRUE() -> TRUE
A33: 32 | B33: 2026 | D33: =TRUE() -> TRUE
A34: 33 | B34: 2027 | D34: =TRUE() -> TRUE
A35: 34 | B35: 2028 | D35: =TRUE() -> TRUE

Sheet extensions
A1: To be specified

Sheet SUTstructure
A2: The supply and use structure here applies only to the mat files used in the procedures
A3: The templates for the data exchange with CML and other partner still have to be specified
A5: For reading the data from CREEA the format specfied here is assumed to be a subset of the format used in the mat files (especially differences after row 212 in the use table are ok)
A7: Supply Table:
C8: 2 dim array with prod x (ind + total imports)
D9: other columns in the supply table were removed compared to CREEA because of data doubling
D10: there will be a matlab function which puts this data back for presentation in xls (TODO)
A13: Use Table
C14: 3 dim array with (pro + va(without Z categories)) x (ind + findemand) x (layers)
D15: All Z categories (employment related stuff) gets removed from the CREEA classification
C17: Layers: | D17: In difference to CREEA, the supply table is not longer part of the use table layer structure!

Sheet readme
A1: The classificiation is based on the CREEA classificiation 2013 (CREEA Classifications2013.xls)
A2: However, as the classification in CREEA is not consistent, the classification here should be used for all DESIRE stuff
A4: Countries are defined separatley in meta/countries
A6: Sheets
G7: url
A8: products | C8: CPA 2008 | F8: eurostat
C9: CPC version 2 | F9: Unstat
C10: correspondance | G10: http://circa.europa.eu/irc/dsis/nacecpacon/info/data/en/correspondence%20table%20cpa%202008%20-%20cpc%20ver%202.pdf
C12: trade and transport margins | G12: These must be negative in the final supply use tables
C13: waste | G13: These are set zero across rows in the final table
A14: industries
C15: NACE Rev. 2 | F15: eurostat
C16: ISIC Rev. 4 | F16: Unstat
C17: correspondance | G17: http://unstats.un.org/unsd/cr/registry/regso.asp?Ci=70&Lg=1
C19: The ISIC correspondece is important already in the compilation of the SUT b/c it is used to map the macro economic constraints of the UN to the industries in the balancing
